llama_index/embeddings/textembed/__init__.py
llama_index/embeddings/textembed/base.py
llama_index_embeddings_textembed-0.3.1.dist-info/METADATA
llama_index_embeddings_textembed-0.3.1.dist-info/WHEEL
llama_index_embeddings_textembed-0.3.1.dist-info/licenses/LICENSE
llama_index_embeddings_textembed-0.3.1.dist-info/RECORD
