Metadata-Version: 2.4
Name: llama-index-embeddings-textembed
Version: 0.3.1
Summary: Integration of TextEmbed with llama-index for embeddings.
Author-email: Keval Dekivadiya <kevaldekivadiya2415@gmail.com>
License-Expression: MIT
License-File: LICENSE
Requires-Python: <4.0,>=3.9
Requires-Dist: aiohttp
Requires-Dist: llama-index-core<0.15,>=0.13.0
